getup/__init__.py
getup/conf.py
getup/get.py
getup/middleware.py
getup/set.py
getup/up.py
getup/wsgi.py
getup-0.0.21.dist-info/entry_points.txt
getup-0.0.21.dist-info/LICENSE
getup-0.0.21.dist-info/WHEEL
getup-0.0.21.dist-info/METADATA
getup-0.0.21.dist-info/RECORD
