Metadata-Version: 2.1
Name: getup
Version: 0.0.21
Summary: Projectless Django setup tool
Home-page: https://gitlab.com/jussiarpalahti/getup
License: MPL-2.0
Author: Jussi Arpalahti
Author-email: jussi.arpalahti@gmail.com
Requires-Python: >=3.7,<4.0
Classifier: License :: OSI Approved
Classifier: Programming Language :: Python :: 3
Classifier: Programming Language :: Python :: 3.7
Requires-Dist: dj_database_url (>=0.5.0,<0.6.0)
Requires-Dist: django (>=2.1,<3.0)
Requires-Dist: django-cors-headers (>=2.4,<3.0)
Requires-Dist: django-environ (>=0.4.5,<0.5.0)
Requires-Dist: dnspython (>=1.16,<2.0)
Requires-Dist: email-validator (>=1.0,<2.0)
Requires-Dist: pydantic (>=0.19.0,<0.20.0)
Project-URL: Repository, https://gitlab.com/jussiarpalahti/getup
